pyimgcook/__init__.py
pyimgcook/cook.py
pyimgcook-0.0.1a2.dist-info/LICENSE
pyimgcook-0.0.1a2.dist-info/METADATA
pyimgcook-0.0.1a2.dist-info/WHEEL
pyimgcook-0.0.1a2.dist-info/top_level.txt
pyimgcook-0.0.1a2.dist-info/RECORD
